craytraverse/__init__.py
craytraverse/craytraverse.cpython-310-darwin.so
craytraverse/cal/rayinit.cal
craytraverse/cal/scbins.cal
craytraverse/cal/tmesh.cal
craytraverse/crenderer/__init__.py
craytraverse/crenderer/rcontrib_c.cpython-310-darwin.so
craytraverse/crenderer/rtrace_c.cpython-310-darwin.so
craytraverse/renderer/__init__.py
craytraverse/renderer/rcontrib.py
craytraverse/renderer/renderer.py
craytraverse/renderer/rtrace.py
craytraverse-0.1.6.data/data/bin/cnt
craytraverse-0.1.6.data/data/bin/gendaylit
craytraverse-0.1.6.data/data/bin/getinfo
craytraverse-0.1.6.data/data/bin/oconv
craytraverse-0.1.6.data/data/bin/pcomb
craytraverse-0.1.6.data/data/bin/pcompos
craytraverse-0.1.6.data/data/bin/pfilt
craytraverse-0.1.6.data/data/bin/pvalue
craytraverse-0.1.6.data/data/bin/rcalc
craytraverse-0.1.6.data/data/bin/rcontrib
craytraverse-0.1.6.data/data/bin/rtrace
craytraverse-0.1.6.data/data/bin/total
craytraverse-0.1.6.data/data/bin/vwrays
craytraverse-0.1.6.data/data/bin/xform
craytraverse-0.1.6.dist-info/LICENSE
craytraverse-0.1.6.dist-info/METADATA
craytraverse-0.1.6.dist-info/WHEEL
craytraverse-0.1.6.dist-info/top_level.txt
craytraverse-0.1.6.dist-info/RECORD
