Metadata-Version: 2.1
Name: craytraverse
Version: 0.1.6
Summary: adaptive sampling for CBDM
Home-page: https://github.com/stephanwaz/raytraverse
Author: Stephen Wasilewski
Author-email: stephanwaz@gmail.com
License: Mozilla Public License 2.0 (MPL 2.0)
Keywords: craytraverse
Classifier: Development Status :: 2 - Pre-Alpha
Classifier: License :: OSI Approved :: Mozilla Public License 2.0 (MPL 2.0)
Classifier: Natural Language :: English
Classifier: Programming Language :: Python :: 3.7
Classifier: Programming Language :: Python :: 3.8
Classifier: Programming Language :: Python :: 3.9
Classifier: Programming Language :: Python :: 3.10
Requires-Python: >=3.7
License-File: LICENSE
Requires-Dist: pybind11
